jewerly/__init__.py
jewerly/client.py
jewerly-0.1.0.dist-info/LICENSE
jewerly-0.1.0.dist-info/METADATA
jewerly-0.1.0.dist-info/WHEEL
jewerly-0.1.0.dist-info/top_level.txt
jewerly-0.1.0.dist-info/RECORD
