Metadata-Version: 2.1
Name: jewerly
Version: 0.1.0
Summary: This can easy to use discord-api.py
Home-page: https://github.com/discord-api-py-org/jewerly
Author: DMS
Author-email: masato190411@gmail.com
License: UNKNOWN
Platform: UNKNOWN
Classifier: Programming Language :: Python :: 3.8
Classifier: License :: OSI Approved :: MIT License
Classifier: Operating System :: OS Independent
License-File: LICENSE
Requires-Dist: discord-api.py (==1.1.0a6)
